{"name":"dun","SubTexture":[{"name":"parts/dun1","x":152,"width":98,"y":262,"height":125},{"name":"parts/guang","x":267,"width":158,"y":192,"height":158},{"name":"parts/guang3","x":252,"width":124,"y":352,"height":123},{"name":"parts/guang2","x":0,"width":265,"y":0,"height":260},{"name":"parts/suidun1","x":427,"width":62,"y":322,"height":124},{"name":"parts/suidun2","x":427,"width":60,"y":192,"height":128},{"name":"parts/suidun","x":267,"width":182,"y":0,"height":190},{"name":"parts/guang4","x":0,"width":150,"y":262,"height":150},{"name":"parts/guang5","x":0,"width":108,"y":414,"height":95}],"imagePath":"texture.png"}