{"frameRate":24,"name":"yx007","armature":[{"name":"yx007","bone":[{"transform":{"skX":0,"scY":1,"x":0,"skY":0,"y":-44,"scX":1},"name":"shenti"},{"transform":{"skX":0,"scY":0.41,"x":-25,"skY":0,"y":-77.95,"scX":1},"name":"guang"},{"transform":{"skX":45,"scY":0.48,"x":35.95,"skY":45,"y":-68.05,"scX":0.8},"name":"guang2"},{"transform":{"skX":0,"scY":1,"x":45,"skY":0,"y":-120.5,"scX":1},"name":"shandian01"},{"transform":{"skX":30,"scY":1,"x":83.45,"skY":30,"y":-123,"scX":1},"name":"shandian02"},{"transform":{"skX":-15,"scY":1,"x":-17.5,"skY":-15,"y":-132.4,"scX":1},"name":"shandian03"}],"skin":[{"slot":[{"name":"shenti","z":0,"display":[{"transform":{"pY":0,"scY":1,"x":-50,"y":-45,"skX":0,"skY":0,"pX":0,"scX":1},"name":"parts/yx007_shenti","type":"image"}],"parent":"shenti"},{"name":"guang","z":1,"display":[{"transform":{"pY":0,"scY":1,"x":-33,"y":-63.95,"skX":0,"skY":0,"pX":0,"scX":1},"name":"parts/yx007_guang1","type":"image"}],"parent":"guang"},{"name":"guang2","z":2,"display":[{"transform":{"pY":0,"scY":1,"x":-32.9,"y":-62.05,"skX":0,"skY":0,"pX":0,"scX":1},"name":"parts/yx007_guang1","type":"image"}],"parent":"guang2"},{"name":"shandian01","z":3,"display":[{"transform":{"pY":0,"scY":1,"x":-9,"y":-37.5,"skX":0,"skY":0,"pX":0,"scX":1},"name":"parts/yx007_shandian","type":"image"}],"parent":"shandian01"},{"name":"shandian02","z":4,"display":[{"transform":{"pY":0,"scY":1,"x":-8.95,"y":-37.55,"skX":0,"skY":0,"pX":0,"scX":1},"name":"parts/yx007_shandian","type":"image"}],"parent":"shandian02"},{"name":"shandian03","z":5,"display":[{"transform":{"pY":0,"scY":1,"x":-9,"y":-37.6,"skX":0,"skY":0,"pX":0,"scX":1},"name":"parts/yx007_shandian","type":"image"}],"parent":"shandian03"}],"name":"default"}],"animation":[{"autoTween":1,"timeline":[{"name":"shenti","scale":1,"frame":[{"transform":{"pY":0,"scY":1,"x":0,"y":-44,"skX":0,"skY":0,"pX":0,"scX":1},"z":0,"duration":9}],"offset":0}],"duration":9,"scale":1,"loop":1,"tweenEasing":null,"name":"huxi","fadeInTime":0.3},{"autoTween":1,"timeline":[{"name":"shenti","scale":1,"frame":[{"z":0,"duration":2,"transform":{"pY":-45,"scY":1,"x":0,"y":1,"skX":0,"skY":0,"pX":0,"scX":1},"tweenEasing":0},{"z":0,"duration":2,"transform":{"pY":-45,"scY":0.79,"x":0,"y":1,"skX":-6.83,"skY":0,"pX":0,"scX":1},"tweenEasing":0},{"z":0,"duration":8,"transform":{"pY":-45,"scY":1.08,"x":0,"y":1,"skX":8.84,"skY":0,"pX":0,"scX":1},"tweenEasing":0},{"transform":{"pY":-45,"scY":1,"x":0,"y":1,"skX":0,"skY":0,"pX":0,"scX":1},"z":0,"duration":4},{"transform":{"pY":-45,"scY":1,"x":0,"y":1,"skX":0,"skY":0,"pX":0,"scX":1},"z":0,"duration":13}],"offset":0},{"name":"guang","scale":1,"frame":[{"z":1,"duration":2,"transform":{"pY":0,"scY":0.41,"x":-25,"y":-77.95,"skX":0,"skY":0,"pX":0,"scX":1},"colorTransform":{"aM":38,"rM":100,"aO":0,"gM":100,"rO":0,"bM":100,"gO":0,"bO":0},"tweenEasing":0},{"z":1,"duration":2,"transform":{"pY":0.95,"scY":0.49,"x":-33,"y":-62.95,"skX":0,"skY":0,"pX":0,"scX":1},"colorTransform":{"aM":53,"rM":100,"aO":0,"gM":100,"rO":0,"bM":100,"gO":0,"bO":0},"tweenEasing":0},{"z":1,"duration":7,"transform":{"pY":0.95,"scY":0.77,"x":-13,"y":-84.45,"skX":0,"skY":0,"pX":0,"scX":1},"tweenEasing":0},{"z":1,"duration":5,"transform":{"pY":0.95,"scY":1,"x":-25.5,"y":-78.95,"skX":0,"skY":0,"pX":0,"scX":1},"tweenEasing":0},{"z":1,"duration":13,"transform":{"pY":0,"scY":0.41,"x":-25,"y":-77.95,"skX":0,"skY":0,"pX":0,"scX":1},"colorTransform":{"aM":38,"rM":100,"aO":0,"gM":100,"rO":0,"bM":100,"gO":0,"bO":0}}],"offset":0},{"name":"guang2","scale":1,"frame":[{"z":2,"duration":2,"transform":{"pY":0,"scY":0.48,"x":35.95,"y":-68.05,"skX":45,"skY":45,"pX":0,"scX":0.8},"colorTransform":{"aM":38,"rM":100,"aO":0,"gM":100,"rO":0,"bM":100,"gO":0,"bO":0},"tweenEasing":0},{"z":2,"duration":2,"transform":{"pY":0,"scY":0.67,"x":29.45,"y":-55.05,"skX":37.78,"skY":37.78,"pX":0,"scX":0.84},"colorTransform":{"aM":64,"rM":100,"aO":0,"gM":100,"rO":0,"bM":100,"gO":0,"bO":0},"tweenEasing":0},{"z":2,"duration":7,"transform":{"pY":-0.15,"scY":0.79,"x":47.4,"y":-72.95,"skX":46.06,"skY":46.06,"pX":0,"scX":0.85},"tweenEasing":0},{"z":2,"duration":5,"transform":{"pY":-0.15,"scY":0.79,"x":36.95,"y":-68.55,"skX":41.14,"skY":41.14,"pX":0.1,"scX":0.87},"tweenEasing":0},{"z":2,"duration":13,"transform":{"pY":0,"scY":0.48,"x":35.95,"y":-68.05,"skX":45,"skY":45,"pX":0,"scX":0.8},"colorTransform":{"aM":38,"rM":100,"aO":0,"gM":100,"rO":0,"bM":100,"gO":0,"bO":0}}],"offset":0},{"name":"shandian01","scale":1,"frame":[{"duration":4,"displayIndex":-1},{"z":3,"duration":2,"transform":{"pY":0,"scY":1,"x":45,"y":-120.5,"skX":0,"skY":0,"pX":0,"scX":1},"tweenEasing":0},{"z":3,"duration":6,"transform":{"pY":0,"scY":1.31,"x":42.5,"y":-137,"skX":0,"skY":0,"pX":0,"scX":1},"colorTransform":{"aM":0,"rM":100,"aO":0,"gM":100,"rO":0,"bM":100,"gO":0,"bO":0}},{"duration":17,"displayIndex":-1}],"offset":0},{"name":"shandian02","scale":1,"frame":[{"duration":4,"displayIndex":-1},{"z":4,"duration":2,"transform":{"pY":0,"scY":1,"x":83.45,"y":-123,"skX":30,"skY":30,"pX":0,"scX":1},"tweenEasing":0},{"z":4,"duration":6,"transform":{"pY":0.05,"scY":1.31,"x":80.5,"y":-131.5,"skX":30,"skY":30,"pX":0,"scX":1},"colorTransform":{"aM":0,"rM":100,"aO":0,"gM":100,"rO":0,"bM":100,"gO":0,"bO":0}},{"duration":17,"displayIndex":-1}],"offset":0},{"name":"shandian03","scale":1,"frame":[{"duration":4,"displayIndex":-1},{"z":5,"duration":2,"transform":{"pY":0,"scY":1,"x":-17.5,"y":-132.4,"skX":-15,"skY":-15,"pX":0,"scX":1},"tweenEasing":0},{"z":5,"duration":6,"transform":{"pY":0.1,"scY":1.31,"x":-34.35,"y":-169.5,"skX":-15,"skY":-15,"pX":0.05,"scX":1},"colorTransform":{"aM":0,"rM":100,"aO":0,"gM":100,"rO":0,"bM":100,"gO":0,"bO":0}},{"duration":17,"displayIndex":-1}],"offset":0}],"duration":29,"scale":1,"loop":1,"tweenEasing":null,"name":"gj01","fadeInTime":0}]}],"version":2.3}