{"name":"jineng011","SubTexture":[{"name":"parts/jineng011_shenti","x":0,"width":316,"y":0,"height":308},{"name":"parts/jineng011_01","x":107,"width":107,"y":310,"height":60},{"name":"parts/jineng011_02","x":216,"width":107,"y":321,"height":60},{"name":"parts/jineng011_03","x":425,"width":59,"y":0,"height":106},{"name":"parts/jineng011_04","x":425,"width":59,"y":108,"height":106},{"name":"parts/jineng011_05","x":318,"width":105,"y":214,"height":105},{"name":"parts/jineng011_06","x":0,"width":105,"y":310,"height":105},{"name":"parts/jineng011_07","x":318,"width":105,"y":0,"height":105},{"name":"parts/jineng011_08","x":318,"width":105,"y":107,"height":105}],"imagePath":"texture.png"}