{"name":"gw002","SubTexture":[{"name":"parts/gw002_bianzi","x":419,"width":80,"y":246,"height":44},{"name":"parts/gw002_bianzi01","x":415,"width":80,"y":292,"height":44},{"name":"parts/gw002_gebo","x":420,"width":58,"y":82,"height":80},{"name":"parts/gw002_gebo01","x":420,"width":58,"y":0,"height":80},{"name":"parts/gw002_gebo02","x":420,"width":58,"y":164,"height":80},{"name":"parts/gw002_shenti","x":0,"width":208,"y":0,"height":240},{"name":"parts/gw002_zui","x":199,"width":168,"y":292,"height":48},{"name":"parts/gw002_bizi","x":480,"width":27,"y":0,"height":15},{"name":"parts/gw002_yan1","x":369,"width":44,"y":337,"height":44},{"name":"parts/gw002_yan2","x":369,"width":48,"y":242,"height":47},{"name":"parts/gw002_shenti01","x":210,"width":208,"y":0,"height":240},{"name":"parts/gw002_shenti02","x":0,"width":197,"y":242,"height":241},{"name":"parts/gw002_yan3","x":369,"width":44,"y":291,"height":44},{"name":"parts/gw002_zui01","x":199,"width":168,"y":242,"height":48}],"imagePath":"texture.png"}